Metadata-Version: 2.1
Name: dash-slick
Version: 0.0.4
Summary: React Slick Dash Components
Home-page: https://github.com/jackskerman/dash-slick
Author: Jack Skerman <jack.skerm@gmail.com>
License: MIT
Platform: UNKNOWN
Classifier: Framework :: Dash
